{
  "$schema": "https://developer.microsoft.com/json-schemas/fabric/item/report/definition/visualContainer/2.1.0/schema.json",
  "name": "2062640eb3adaa3e0941",
  "position": {
    "x": 500.07180843884134,
    "y": 118.1761736360446,
    "z": 9000,
    "height": 150.51912642064627,
    "width": 422.94630564479115,
    "tabOrder": 8000
  },
  "visual": {
    "visualType": "lineChart",
    "query": {
      "queryState": {
        "Category": {
          "projections": [
            {
              "field": {
                "Column": {
                  "Expression": {
                    "SourceRef": {
                      "Entity": "Dates"
                    }
                  },
                  "Property": "MonthNameShort"
                }
              },
              "queryRef": "Dates.MonthNameShort",
              "nativeQueryRef": "MonthNameShort",
              "active": true
            }
          ]
        },
        "Y": {
          "projections": [
            {
              "field": {
                "Measure": {
                  "Expression": {
                    "SourceRef": {
                      "Entity": "_Measures"
                    }
                  },
                  "Property": "Total Patients"
                }
              },
              "queryRef": "_Measures.Total Patients",
              "nativeQueryRef": "Total Patients"
            },
            {
              "field": {
                "Measure": {
                  "Expression": {
                    "SourceRef": {
                      "Entity": "_Measures"
                    }
                  },
                  "Property": "Values Max Point (MonTH)"
                }
              },
              "queryRef": "_Measures.Values Max Point (MonTH)",
              "nativeQueryRef": "Values Max Point (MonTH)"
            }
          ]
        }
      }
    },
    "objects": {
      "lineStyles": [
        {
          "properties": {
            "showMarker": {
              "expr": {
                "Literal": {
                  "Value": "false"
                }
              }
            },
            "lineChartType": {
              "expr": {
                "Literal": {
                  "Value": "'smooth'"
                }
              }
            }
          }
        }
      ],
      "dataPoint": [
        {
          "properties": {
            "fill": {
              "solid": {
                "color": {
                  "expr": {
                    "Conditional": {
                      "Cases": [
                        {
                          "Condition": {
                            "Comparison": {
                              "ComparisonKind": 0,
                              "Left": {
                                "Measure": {
                                  "Expression": {
                                    "SourceRef": {
                                      "Entity": "_Measures"
                                    }
                                  },
                                  "Property": "CF Max Point (MonTH)"
                                }
                              },
                              "Right": {
                                "Literal": {
                                  "Value": "1D"
                                }
                              }
                            }
                          },
                          "Value": {
                            "Literal": {
                              "Value": "'#13C9F2'"
                            }
                          }
                        },
                        {
                          "Condition": {
                            "Comparison": {
                              "ComparisonKind": 0,
                              "Left": {
                                "Measure": {
                                  "Expression": {
                                    "SourceRef": {
                                      "Entity": "_Measures"
                                    }
                                  },
                                  "Property": "CF Max Point (MonTH)"
                                }
                              },
                              "Right": {
                                "Literal": {
                                  "Value": "0D"
                                }
                              }
                            }
                          },
                          "Value": {
                            "Literal": {
                              "Value": "'#F20505'"
                            }
                          }
                        }
                      ]
                    }
                  }
                }
              }
            }
          },
          "selector": {
            "data": [
              {
                "dataViewWildcard": {
                  "matchingOption": 1
                }
              }
            ]
          }
        }
      ],
      "labels": [
        {
          "properties": {
            "show": {
              "expr": {
                "Literal": {
                  "Value": "true"
                }
              }
            }
          }
        },
        {
          "properties": {
            "showSeries": {
              "expr": {
                "Literal": {
                  "Value": "false"
                }
              }
            },
            "labelDisplayUnits": {
              "expr": {
                "Literal": {
                  "Value": "1D"
                }
              }
            },
            "labelPrecision": {
              "expr": {
                "Literal": {
                  "Value": "0L"
                }
              }
            },
            "bold": {
              "expr": {
                "Literal": {
                  "Value": "true"
                }
              }
            },
            "fontSize": {
              "expr": {
                "Literal": {
                  "Value": "10D"
                }
              }
            }
          },
          "selector": {
            "metadata": "_Measures.Total Patients"
          }
        }
      ],
      "legend": [
        {
          "properties": {
            "show": {
              "expr": {
                "Literal": {
                  "Value": "false"
                }
              }
            }
          }
        }
      ],
      "valueAxis": [
        {
          "properties": {
            "show": {
              "expr": {
                "Literal": {
                  "Value": "false"
                }
              }
            },
            "showAxisTitle": {
              "expr": {
                "Literal": {
                  "Value": "false"
                }
              }
            }
          }
        }
      ],
      "categoryAxis": [
        {
          "properties": {
            "bold": {
              "expr": {
                "Literal": {
                  "Value": "true"
                }
              }
            },
            "fontSize": {
              "expr": {
                "Literal": {
                  "Value": "10D"
                }
              }
            },
            "showAxisTitle": {
              "expr": {
                "Literal": {
                  "Value": "true"
                }
              }
            }
          }
        }
      ]
    },
    "visualContainerObjects": {
      "title": [
        {
          "properties": {
            "text": {
              "expr": {
                "Literal": {
                  "Value": "'Total Patients Visits'"
                }
              }
            }
          }
        }
      ]
    },
    "drillFilterOtherVisuals": true
  }
}